models/__init__.py
models/item.py
models/stores.py
models/user.py
resources/__init__.py
resources/item.py
resources/stores.py
resources/user.py
thflask/__init__.py
thflask/app.py
thflask/db.py
thflask/security.py
thflask/models/__init__.py
thflask/models/item.py
thflask/models/stores.py
thflask/models/user.py
thflask/resources/__init__.py
thflask/resources/item.py
thflask/resources/stores.py
thflask/resources/user.py
thflask-0.1.1.data/scripts/start-flask
thflask-0.1.1.data/scripts/thflask
thflask-0.1.1.dist-info/LICENCE
thflask-0.1.1.dist-info/METADATA
thflask-0.1.1.dist-info/WHEEL
thflask-0.1.1.dist-info/top_level.txt
thflask-0.1.1.dist-info/RECORD
