Metadata-Version: 2.1
Name: thflask
Version: 0.1.1
Summary: Flask application that implements an items database
Home-page: https://github.com/themisAnagno/th-flask.git
Author: Themis Anagnostopoulos
Author-email: thmanagnostopoulos@gmail.com
License: MIT
Download-URL: https://github.com/themisAnagno/th-flask/archive/v0.1.0.zip
Platform: UNKNOWN
Classifier: License :: OSI Approved :: MIT License
Classifier: Programming Language :: Python
Classifier: Programming Language :: Python :: 3
Classifier: Programming Language :: Python :: 3.7
Classifier: Programming Language :: Python :: Implementation :: CPython
Classifier: Programming Language :: Python :: Implementation :: PyPy
Requires-Python: >=3.7.0
Requires-Dist: flask
Requires-Dist: flask-restful
Requires-Dist: flask-jwt
Requires-Dist: flask-sqlalchemy
Requires-Dist: uwsgi
Requires-Dist: psycopg2-binary
